TwitchX/__init__.py
TwitchX/api.py
TwitchX/cache.py
TwitchX/stream.py
TwitchX/error/__init__.py
TwitchX/ext/__init__.py
TwitchX/ext/GraphQL/__init__.py
TwitchX/ext/login/__init__.py
TwitchX/ext/login/browser/__init__.py
TwitchX/ext/login/browser/_chrome.py
TwitchX/ext/login/gmail/__init__.py
TwitchX/ext/parser/__init__.py
TwitchX/ext/parser/get_vendorjs.py
TwitchX/ext/parser/gql_client_id.py
TwitchX/helix/__init__.py
TwitchX/helix/helix.py
TwitchX/helix/model/__init__.py
TwitchX/helix/model/global_model.py
TwitchX/helix/model/search/__init__.py
TwitchX/helix/model/streams/__init__.py
TwitchX/helix/model/users/__init__.py
TwitchX/helix/model/webhooks/__init__.py
TwitchX/helix/resource/__init__.py
TwitchX/helix/resource/search/__init__.py
TwitchX/helix/resource/streams/__init__.py
TwitchX/helix/resource/users/__init__.py
TwitchX/helix/resource/webhooks/__init__.py
TwitchX/util/__init__.py
TwitchX/util/_http.py
TwitchX-1.2.7.dist-info/LICENSE
TwitchX-1.2.7.dist-info/METADATA
TwitchX-1.2.7.dist-info/WHEEL
TwitchX-1.2.7.dist-info/top_level.txt
TwitchX-1.2.7.dist-info/RECORD
