Metadata-Version: 2.1
Name: TwitchX
Version: 1.2.7
Summary: Netchive Twitch Extension
Home-page: https://netchive.com/
Author: Netchive™ Team
Author-email: contact@netchive.com
License: UNKNOWN
Keywords: TwitchX,Twitch,Netchive,Extension
Platform: UNKNOWN
Classifier: Programming Language :: Python :: 3.8
Classifier: Topic :: Software Development :: Libraries :: Python Modules
Classifier: License :: Free for non-commercial use
Classifier: Development Status :: 3 - Alpha
Requires-Dist: gql[all]
Requires-Dist: pydantic
Requires-Dist: ujson
Requires-Dist: user-agent
Requires-Dist: browser-cookie3
Requires-Dist: requests
Requires-Dist: selenium
Requires-Dist: scrapy
Requires-Dist: gql[aiohttp] (==3.0.0a5)
Requires-Dist: beautifulsoup4
Requires-Dist: lxml
